{"id":"../node_modules/rc-select/es/util.js","dependencies":[{"name":"/home/jacky/文档/nodejs_test/Koa2/douban-trailer-imooc/node_modules/rc-select/package.json","includedInParent":true,"mtime":1535526839084},{"name":"/home/jacky/文档/nodejs_test/Koa2/douban-trailer-imooc/package.json","includedInParent":true,"mtime":1535632897471},{"name":"/home/jacky/文档/nodejs_test/Koa2/douban-trailer-imooc/.babelrc","includedInParent":true,"mtime":1535339569417},{"name":"react","loc":{"line":1,"column":18},"parent":"/home/jacky/文档/nodejs_test/Koa2/douban-trailer-imooc/node_modules/rc-select/es/util.js","resolved":"/home/jacky/文档/nodejs_test/Koa2/douban-trailer-imooc/node_modules/react/index.js"}],"generated":{"js":"'use strict';\n\nObject.defineProperty(exports, \"__esModule\", {\n  value: true\n});\nexports.UNSELECTABLE_ATTRIBUTE = exports.UNSELECTABLE_STYLE = undefined;\nexports.getValuePropValue = getValuePropValue;\nexports.getPropValue = getPropValue;\nexports.isMultiple = isMultiple;\nexports.isCombobox = isCombobox;\nexports.isMultipleOrTags = isMultipleOrTags;\nexports.isMultipleOrTagsOrCombobox = isMultipleOrTagsOrCombobox;\nexports.isSingleMode = isSingleMode;\nexports.toArray = toArray;\nexports.preventDefaultEvent = preventDefaultEvent;\nexports.findIndexInValueByKey = findIndexInValueByKey;\nexports.findIndexInValueByLabel = findIndexInValueByLabel;\nexports.getSelectKeys = getSelectKeys;\nexports.findFirstMenuItem = findFirstMenuItem;\nexports.includesSeparators = includesSeparators;\nexports.splitBySeparators = splitBySeparators;\nexports.defaultFilterFn = defaultFilterFn;\nexports.validateOptionValue = validateOptionValue;\nexports.saveRef = saveRef;\n\nvar _react = require('react');\n\nvar _react2 = _interopRequireDefault(_react);\n\nfunction _interopRequireDefault(obj) { return obj && obj.__esModule ? obj : { default: obj }; }\n\nfunction getValuePropValue(child) {\n  var props = child.props;\n  if ('value' in props) {\n    return props.value;\n  }\n  if (child.key) {\n    return child.key;\n  }\n  if (child.type && child.type.isSelectOptGroup && props.label) {\n    return props.label;\n  }\n  throw new Error('Need at least a key or a value or a label (only for OptGroup) for ' + child);\n}\n\nfunction getPropValue(child, prop) {\n  if (prop === 'value') {\n    return getValuePropValue(child);\n  }\n  return child.props[prop];\n}\n\nfunction isMultiple(props) {\n  return props.multiple;\n}\n\nfunction isCombobox(props) {\n  return props.combobox;\n}\n\nfunction isMultipleOrTags(props) {\n  return props.multiple || props.tags;\n}\n\nfunction isMultipleOrTagsOrCombobox(props) {\n  return isMultipleOrTags(props) || isCombobox(props);\n}\n\nfunction isSingleMode(props) {\n  return !isMultipleOrTagsOrCombobox(props);\n}\n\nfunction toArray(value) {\n  var ret = value;\n  if (value === undefined) {\n    ret = [];\n  } else if (!Array.isArray(value)) {\n    ret = [value];\n  }\n  return ret;\n}\n\nfunction preventDefaultEvent(e) {\n  e.preventDefault();\n}\n\nfunction findIndexInValueByKey(value, key) {\n  var index = -1;\n  for (var i = 0; i < value.length; i++) {\n    if (value[i].key === key) {\n      index = i;\n      break;\n    }\n  }\n  return index;\n}\n\nfunction findIndexInValueByLabel(value, label) {\n  var index = -1;\n  for (var i = 0; i < value.length; i++) {\n    if (toArray(value[i].label).join('') === label) {\n      index = i;\n      break;\n    }\n  }\n  return index;\n}\n\nfunction getSelectKeys(menuItems, value) {\n  if (value === null || value === undefined) {\n    return [];\n  }\n  var selectedKeys = [];\n  _react2.default.Children.forEach(menuItems, function (item) {\n    if (item.type.isMenuItemGroup) {\n      selectedKeys = selectedKeys.concat(getSelectKeys(item.props.children, value));\n    } else {\n      var itemValue = getValuePropValue(item);\n      var itemKey = item.key;\n      if (findIndexInValueByKey(value, itemValue) !== -1 && itemKey) {\n        selectedKeys.push(itemKey);\n      }\n    }\n  });\n  return selectedKeys;\n}\n\nvar UNSELECTABLE_STYLE = exports.UNSELECTABLE_STYLE = {\n  userSelect: 'none',\n  WebkitUserSelect: 'none'\n};\n\nvar UNSELECTABLE_ATTRIBUTE = exports.UNSELECTABLE_ATTRIBUTE = {\n  unselectable: 'unselectable'\n};\n\nfunction findFirstMenuItem(children) {\n  for (var i = 0; i < children.length; i++) {\n    var child = children[i];\n    if (child.type.isMenuItemGroup) {\n      var found = findFirstMenuItem(child.props.children);\n      if (found) {\n        return found;\n      }\n    } else if (!child.props.disabled) {\n      return child;\n    }\n  }\n  return null;\n}\n\nfunction includesSeparators(string, separators) {\n  for (var i = 0; i < separators.length; ++i) {\n    if (string.lastIndexOf(separators[i]) > 0) {\n      return true;\n    }\n  }\n  return false;\n}\n\nfunction splitBySeparators(string, separators) {\n  var reg = new RegExp('[' + separators.join() + ']');\n  return string.split(reg).filter(function (token) {\n    return token;\n  });\n}\n\nfunction defaultFilterFn(input, child) {\n  return String(getPropValue(child, this.props.optionFilterProp)).indexOf(input) > -1;\n}\n\nfunction validateOptionValue(value, props) {\n  if (isSingleMode(props) || isMultiple(props)) {\n    return;\n  }\n  if (typeof value !== 'string') {\n    throw new Error('Invalid `value` of type `' + typeof value + '` supplied to Option, ' + 'expected `string` when `tags/combobox` is `true`.');\n  }\n}\n\nfunction saveRef(instance, name) {\n  return function (node) {\n    instance[name] = node;\n  };\n}","map":{"mappings":[{"name":"getValuePropValue","generated":{"line":7,"column":8},"source":"../node_modules/rc-select/es/util.js","original":{"line":3,"column":16}},{"name":"getValuePropValue","generated":{"line":7,"column":28},"source":"../node_modules/rc-select/es/util.js","original":{"line":3,"column":16}},{"name":"getPropValue","generated":{"line":8,"column":8},"source":"../node_modules/rc-select/es/util.js","original":{"line":17,"column":16}},{"name":"getPropValue","generated":{"line":8,"column":23},"source":"../node_modules/rc-select/es/util.js","original":{"line":17,"column":16}},{"name":"isMultiple","generated":{"line":9,"column":8},"source":"../node_modules/rc-select/es/util.js","original":{"line":24,"column":16}},{"name":"isMultiple","generated":{"line":9,"column":21},"source":"../node_modules/rc-select/es/util.js","original":{"line":24,"column":16}},{"name":"isCombobox","generated":{"line":10,"column":8},"source":"../node_modules/rc-select/es/util.js","original":{"line":28,"column":16}},{"name":"isCombobox","generated":{"line":10,"column":21},"source":"../node_modules/rc-select/es/util.js","original":{"line":28,"column":16}},{"name":"isMultipleOrTags","generated":{"line":11,"column":8},"source":"../node_modules/rc-select/es/util.js","original":{"line":32,"column":16}},{"name":"isMultipleOrTags","generated":{"line":11,"column":27},"source":"../node_modules/rc-select/es/util.js","original":{"line":32,"column":16}},{"name":"isMultipleOrTagsOrCombobox","generated":{"line":12,"column":8},"source":"../node_modules/rc-select/es/util.js","original":{"line":36,"column":16}},{"name":"isMultipleOrTagsOrCombobox","generated":{"line":12,"column":37},"source":"../node_modules/rc-select/es/util.js","original":{"line":36,"column":16}},{"name":"isSingleMode","generated":{"line":13,"column":8},"source":"../node_modules/rc-select/es/util.js","original":{"line":40,"column":16}},{"name":"isSingleMode","generated":{"line":13,"column":23},"source":"../node_modules/rc-select/es/util.js","original":{"line":40,"column":16}},{"name":"toArray","generated":{"line":14,"column":8},"source":"../node_modules/rc-select/es/util.js","original":{"line":44,"column":16}},{"name":"toArray","generated":{"line":14,"column":18},"source":"../node_modules/rc-select/es/util.js","original":{"line":44,"column":16}},{"name":"preventDefaultEvent","generated":{"line":15,"column":8},"source":"../node_modules/rc-select/es/util.js","original":{"line":54,"column":16}},{"name":"preventDefaultEvent","generated":{"line":15,"column":30},"source":"../node_modules/rc-select/es/util.js","original":{"line":54,"column":16}},{"name":"findIndexInValueByKey","generated":{"line":16,"column":8},"source":"../node_modules/rc-select/es/util.js","original":{"line":58,"column":16}},{"name":"findIndexInValueByKey","generated":{"line":16,"column":32},"source":"../node_modules/rc-select/es/util.js","original":{"line":58,"column":16}},{"name":"findIndexInValueByLabel","generated":{"line":17,"column":8},"source":"../node_modules/rc-select/es/util.js","original":{"line":69,"column":16}},{"name":"findIndexInValueByLabel","generated":{"line":17,"column":34},"source":"../node_modules/rc-select/es/util.js","original":{"line":69,"column":16}},{"name":"getSelectKeys","generated":{"line":18,"column":8},"source":"../node_modules/rc-select/es/util.js","original":{"line":80,"column":16}},{"name":"getSelectKeys","generated":{"line":18,"column":24},"source":"../node_modules/rc-select/es/util.js","original":{"line":80,"column":16}},{"name":"findFirstMenuItem","generated":{"line":19,"column":8},"source":"../node_modules/rc-select/es/util.js","original":{"line":108,"column":16}},{"name":"findFirstMenuItem","generated":{"line":19,"column":28},"source":"../node_modules/rc-select/es/util.js","original":{"line":108,"column":16}},{"name":"includesSeparators","generated":{"line":20,"column":8},"source":"../node_modules/rc-select/es/util.js","original":{"line":123,"column":16}},{"name":"includesSeparators","generated":{"line":20,"column":29},"source":"../node_modules/rc-select/es/util.js","original":{"line":123,"column":16}},{"name":"splitBySeparators","generated":{"line":21,"column":8},"source":"../node_modules/rc-select/es/util.js","original":{"line":132,"column":16}},{"name":"splitBySeparators","generated":{"line":21,"column":28},"source":"../node_modules/rc-select/es/util.js","original":{"line":132,"column":16}},{"name":"defaultFilterFn","generated":{"line":22,"column":8},"source":"../node_modules/rc-select/es/util.js","original":{"line":139,"column":16}},{"name":"defaultFilterFn","generated":{"line":22,"column":26},"source":"../node_modules/rc-select/es/util.js","original":{"line":139,"column":16}},{"name":"validateOptionValue","generated":{"line":23,"column":8},"source":"../node_modules/rc-select/es/util.js","original":{"line":143,"column":16}},{"name":"validateOptionValue","generated":{"line":23,"column":30},"source":"../node_modules/rc-select/es/util.js","original":{"line":143,"column":16}},{"name":"saveRef","generated":{"line":24,"column":8},"source":"../node_modules/rc-select/es/util.js","original":{"line":152,"column":16}},{"name":"saveRef","generated":{"line":24,"column":18},"source":"../node_modules/rc-select/es/util.js","original":{"line":152,"column":16}},{"generated":{"line":26,"column":0},"source":"../node_modules/rc-select/es/util.js","original":{"line":1,"column":0}},{"generated":{"line":32,"column":0},"source":"../node_modules/rc-select/es/util.js","original":{"line":3,"column":7}},{"name":"getValuePropValue","generated":{"line":32,"column":9},"source":"../node_modules/rc-select/es/util.js","original":{"line":3,"column":16}},{"generated":{"line":32,"column":26},"source":"../node_modules/rc-select/es/util.js","original":{"line":3,"column":7}},{"name":"child","generated":{"line":32,"column":27},"source":"../node_modules/rc-select/es/util.js","original":{"line":3,"column":34}},{"generated":{"line":32,"column":32},"source":"../node_modules/rc-select/es/util.js","original":{"line":3,"column":7}},{"generated":{"line":32,"column":34},"source":"../node_modules/rc-select/es/util.js","original":{"line":3,"column":41}},{"generated":{"line":33,"column":0},"source":"../node_modules/rc-select/es/util.js","original":{"line":4,"column":2}},{"name":"props","generated":{"line":33,"column":6},"source":"../node_modules/rc-select/es/util.js","original":{"line":4,"column":6}},{"name":"child","generated":{"line":33,"column":14},"source":"../node_modules/rc-select/es/util.js","original":{"line":4,"column":14}},{"name":"props","generated":{"line":33,"column":20},"source":"../node_modules/rc-select/es/util.js","original":{"line":4,"column":20}},{"generated":{"line":33,"column":25},"source":"../node_modules/rc-select/es/util.js","original":{"line":4,"column":2}},{"generated":{"line":34,"column":0},"source":"../node_modules/rc-select/es/util.js","original":{"line":5,"column":2}},{"generated":{"line":34,"column":6},"source":"../node_modules/rc-select/es/util.js","original":{"line":5,"column":6}},{"name":"props","generated":{"line":34,"column":17},"source":"../node_modules/rc-select/es/util.js","original":{"line":5,"column":17}},{"generated":{"line":34,"column":22},"source":"../node_modules/rc-select/es/util.js","original":{"line":5,"column":2}},{"generated":{"line":34,"column":24},"source":"../node_modules/rc-select/es/util.js","original":{"line":5,"column":24}},{"generated":{"line":35,"column":0},"source":"../node_modules/rc-select/es/util.js","original":{"line":6,"column":4}},{"name":"props","generated":{"line":35,"column":11},"source":"../node_modules/rc-select/es/util.js","original":{"line":6,"column":11}},{"name":"value","generated":{"line":35,"column":17},"source":"../node_modules/rc-select/es/util.js","original":{"line":6,"column":17}},{"generated":{"line":35,"column":22},"source":"../node_modules/rc-select/es/util.js","original":{"line":6,"column":4}},{"generated":{"line":36,"column":0},"source":"../node_modules/rc-select/es/util.js","original":{"line":7,"column":3}},{"generated":{"line":37,"column":0},"source":"../node_modules/rc-select/es/util.js","original":{"line":8,"column":2}},{"name":"child","generated":{"line":37,"column":6},"source":"../node_modules/rc-select/es/util.js","original":{"line":8,"column":6}},{"name":"key","generated":{"line":37,"column":12},"source":"../node_modules/rc-select/es/util.js","original":{"line":8,"column":12}},{"generated":{"line":37,"column":15},"source":"../node_modules/rc-select/es/util.js","original":{"line":8,"column":2}},{"generated":{"line":37,"column":17},"source":"../node_modules/rc-select/es/util.js","original":{"line":8,"column":17}},{"generated":{"line":38,"column":0},"source":"../node_modules/rc-select/es/util.js","original":{"line":9,"column":4}},{"name":"child","generated":{"line":38,"column":11},"source":"../node_modules/rc-select/es/util.js","original":{"line":9,"column":11}},{"name":"key","generated":{"line":38,"column":17},"source":"../node_modules/rc-select/es/util.js","original":{"line":9,"column":17}},{"generated":{"line":38,"column":20},"source":"../node_modules/rc-select/es/util.js","original":{"line":9,"column":4}},{"generated":{"line":39,"column":0},"source":"../node_modules/rc-select/es/util.js","original":{"line":10,"column":3}},{"generated":{"line":40,"column":0},"source":"../node_modules/rc-select/es/util.js","original":{"line":11,"column":2}},{"name":"child","generated":{"line":40,"column":6},"source":"../node_modules/rc-select/es/util.js","original":{"line":11,"column":6}},{"name":"type","generated":{"line":40,"column":12},"source":"../node_modules/rc-select/es/util.js","original":{"line":11,"column":12}},{"generated":{"line":40,"column":16},"source":"../node_modules/rc-select/es/util.js","original":{"line":11,"column":6}},{"name":"child","generated":{"line":40,"column":20},"source":"../node_modules/rc-select/es/util.js","original":{"line":11,"column":20}},{"name":"type","generated":{"line":40,"column":26},"source":"../node_modules/rc-select/es/util.js","original":{"line":11,"column":26}},{"generated":{"line":40,"column":30},"source":"../node_modules/rc-select/es/util.js","original":{"line":11,"column":20}},{"name":"isSelectOptGroup","generated":{"line":40,"column":31},"source":"../node_modules/rc-select/es/util.js","original":{"line":11,"column":31}},{"generated":{"line":40,"column":47},"source":"../node_modules/rc-select/es/util.js","original":{"line":11,"column":6}},{"name":"props","generated":{"line":40,"column":51},"source":"../node_modules/rc-select/es/util.js","original":{"line":11,"column":51}},{"name":"label","generated":{"line":40,"column":57},"source":"../node_modules/rc-select/es/util.js","original":{"line":11,"column":57}},{"generated":{"line":40,"column":62},"source":"../node_modules/rc-select/es/util.js","original":{"line":11,"column":2}},{"generated":{"line":40,"column":64},"source":"../node_modules/rc-select/es/util.js","original":{"line":11,"column":64}},{"generated":{"line":41,"column":0},"source":"../node_modules/rc-select/es/util.js","original":{"line":12,"column":4}},{"name":"props","generated":{"line":41,"column":11},"source":"../node_modules/rc-select/es/util.js","original":{"line":12,"column":11}},{"name":"label","generated":{"line":41,"column":17},"source":"../node_modules/rc-select/es/util.js","original":{"line":12,"column":17}},{"generated":{"line":41,"column":22},"source":"../node_modules/rc-select/es/util.js","original":{"line":12,"column":4}},{"generated":{"line":42,"column":0},"source":"../node_modules/rc-select/es/util.js","original":{"line":13,"column":3}},{"generated":{"line":43,"column":0},"source":"../node_modules/rc-select/es/util.js","original":{"line":14,"column":2}},{"generated":{"line":43,"column":8},"source":"../node_modules/rc-select/es/util.js","original":{"line":14,"column":8}},{"name":"Error","generated":{"line":43,"column":12},"source":"../node_modules/rc-select/es/util.js","original":{"line":14,"column":12}},{"generated":{"line":43,"column":17},"source":"../node_modules/rc-select/es/util.js","original":{"line":14,"column":8}},{"generated":{"line":43,"column":18},"source":"../node_modules/rc-select/es/util.js","original":{"line":14,"column":18}},{"name":"child","generated":{"line":43,"column":89},"source":"../node_modules/rc-select/es/util.js","original":{"line":14,"column":89}},{"generated":{"line":43,"column":94},"source":"../node_modules/rc-select/es/util.js","original":{"line":14,"column":8}},{"generated":{"line":43,"column":95},"source":"../node_modules/rc-select/es/util.js","original":{"line":14,"column":2}},{"generated":{"line":44,"column":0},"source":"../node_modules/rc-select/es/util.js","original":{"line":15,"column":1}},{"generated":{"line":46,"column":0},"source":"../node_modules/rc-select/es/util.js","original":{"line":17,"column":7}},{"name":"getPropValue","generated":{"line":46,"column":9},"source":"../node_modules/rc-select/es/util.js","original":{"line":17,"column":16}},{"generated":{"line":46,"column":21},"source":"../node_modules/rc-select/es/util.js","original":{"line":17,"column":7}},{"name":"child","generated":{"line":46,"column":22},"source":"../node_modules/rc-select/es/util.js","original":{"line":17,"column":29}},{"generated":{"line":46,"column":27},"source":"../node_modules/rc-select/es/util.js","original":{"line":17,"column":7}},{"name":"prop","generated":{"line":46,"column":29},"source":"../node_modules/rc-select/es/util.js","original":{"line":17,"column":36}},{"generated":{"line":46,"column":33},"source":"../node_modules/rc-select/es/util.js","original":{"line":17,"column":7}},{"generated":{"line":46,"column":35},"source":"../node_modules/rc-select/es/util.js","original":{"line":17,"column":42}},{"generated":{"line":47,"column":0},"source":"../node_modules/rc-select/es/util.js","original":{"line":18,"column":2}},{"name":"prop","generated":{"line":47,"column":6},"source":"../node_modules/rc-select/es/util.js","original":{"line":18,"column":6}},{"generated":{"line":47,"column":15},"source":"../node_modules/rc-select/es/util.js","original":{"line":18,"column":15}},{"generated":{"line":47,"column":22},"source":"../node_modules/rc-select/es/util.js","original":{"line":18,"column":2}},{"generated":{"line":47,"column":24},"source":"../node_modules/rc-select/es/util.js","original":{"line":18,"column":24}},{"generated":{"line":48,"column":0},"source":"../node_modules/rc-select/es/util.js","original":{"line":19,"column":4}},{"name":"getValuePropValue","generated":{"line":48,"column":11},"source":"../node_modules/rc-select/es/util.js","original":{"line":19,"column":11}},{"name":"child","generated":{"line":48,"column":29},"source":"../node_modules/rc-select/es/util.js","original":{"line":19,"column":29}},{"generated":{"line":48,"column":34},"source":"../node_modules/rc-select/es/util.js","original":{"line":19,"column":11}},{"generated":{"line":48,"column":35},"source":"../node_modules/rc-select/es/util.js","original":{"line":19,"column":4}},{"generated":{"line":49,"column":0},"source":"../node_modules/rc-select/es/util.js","original":{"line":20,"column":3}},{"generated":{"line":50,"column":0},"source":"../node_modules/rc-select/es/util.js","original":{"line":21,"column":2}},{"name":"child","generated":{"line":50,"column":9},"source":"../node_modules/rc-select/es/util.js","original":{"line":21,"column":9}},{"name":"props","generated":{"line":50,"column":15},"source":"../node_modules/rc-select/es/util.js","original":{"line":21,"column":15}},{"generated":{"line":50,"column":20},"source":"../node_modules/rc-select/es/util.js","original":{"line":21,"column":9}},{"name":"prop","generated":{"line":50,"column":21},"source":"../node_modules/rc-select/es/util.js","original":{"line":21,"column":21}},{"generated":{"line":50,"column":25},"source":"../node_modules/rc-select/es/util.js","original":{"line":21,"column":9}},{"generated":{"line":50,"column":26},"source":"../node_modules/rc-select/es/util.js","original":{"line":21,"column":2}},{"generated":{"line":51,"column":0},"source":"../node_modules/rc-select/es/util.js","original":{"line":22,"column":1}},{"generated":{"line":53,"column":0},"source":"../node_modules/rc-select/es/util.js","original":{"line":24,"column":7}},{"name":"isMultiple","generated":{"line":53,"column":9},"source":"../node_modules/rc-select/es/util.js","original":{"line":24,"column":16}},{"generated":{"line":53,"column":19},"source":"../node_modules/rc-select/es/util.js","original":{"line":24,"column":7}},{"name":"props","generated":{"line":53,"column":20},"source":"../node_modules/rc-select/es/util.js","original":{"line":24,"column":27}},{"generated":{"line":53,"column":25},"source":"../node_modules/rc-select/es/util.js","original":{"line":24,"column":7}},{"generated":{"line":53,"column":27},"source":"../node_modules/rc-select/es/util.js","original":{"line":24,"column":34}},{"generated":{"line":54,"column":0},"source":"../node_modules/rc-select/es/util.js","original":{"line":25,"column":2}},{"name":"props","generated":{"line":54,"column":9},"source":"../node_modules/rc-select/es/util.js","original":{"line":25,"column":9}},{"name":"multiple","generated":{"line":54,"column":15},"source":"../node_modules/rc-select/es/util.js","original":{"line":25,"column":15}},{"generated":{"line":54,"column":23},"source":"../node_modules/rc-select/es/util.js","original":{"line":25,"column":2}},{"generated":{"line":55,"column":0},"source":"../node_modules/rc-select/es/util.js","original":{"line":26,"column":1}},{"generated":{"line":57,"column":0},"source":"../node_modules/rc-select/es/util.js","original":{"line":28,"column":7}},{"name":"isCombobox","generated":{"line":57,"column":9},"source":"../node_modules/rc-select/es/util.js","original":{"line":28,"column":16}},{"generated":{"line":57,"column":19},"source":"../node_modules/rc-select/es/util.js","original":{"line":28,"column":7}},{"name":"props","generated":{"line":57,"column":20},"source":"../node_modules/rc-select/es/util.js","original":{"line":28,"column":27}},{"generated":{"line":57,"column":25},"source":"../node_modules/rc-select/es/util.js","original":{"line":28,"column":7}},{"generated":{"line":57,"column":27},"source":"../node_modules/rc-select/es/util.js","original":{"line":28,"column":34}},{"generated":{"line":58,"column":0},"source":"../node_modules/rc-select/es/util.js","original":{"line":29,"column":2}},{"name":"props","generated":{"line":58,"column":9},"source":"../node_modules/rc-select/es/util.js","original":{"line":29,"column":9}},{"name":"combobox","generated":{"line":58,"column":15},"source":"../node_modules/rc-select/es/util.js","original":{"line":29,"column":15}},{"generated":{"line":58,"column":23},"source":"../node_modules/rc-select/es/util.js","original":{"line":29,"column":2}},{"generated":{"line":59,"column":0},"source":"../node_modules/rc-select/es/util.js","original":{"line":30,"column":1}},{"generated":{"line":61,"column":0},"source":"../node_modules/rc-select/es/util.js","original":{"line":32,"column":7}},{"name":"isMultipleOrTags","generated":{"line":61,"column":9},"source":"../node_modules/rc-select/es/util.js","original":{"line":32,"column":16}},{"generated":{"line":61,"column":25},"source":"../node_modules/rc-select/es/util.js","original":{"line":32,"column":7}},{"name":"props","generated":{"line":61,"column":26},"source":"../node_modules/rc-select/es/util.js","original":{"line":32,"column":33}},{"generated":{"line":61,"column":31},"source":"../node_modules/rc-select/es/util.js","original":{"line":32,"column":7}},{"generated":{"line":61,"column":33},"source":"../node_modules/rc-select/es/util.js","original":{"line":32,"column":40}},{"generated":{"line":62,"column":0},"source":"../node_modules/rc-select/es/util.js","original":{"line":33,"column":2}},{"name":"props","generated":{"line":62,"column":9},"source":"../node_modules/rc-select/es/util.js","original":{"line":33,"column":9}},{"name":"multiple","generated":{"line":62,"column":15},"source":"../node_modules/rc-select/es/util.js","original":{"line":33,"column":15}},{"generated":{"line":62,"column":23},"source":"../node_modules/rc-select/es/util.js","original":{"line":33,"column":9}},{"name":"props","generated":{"line":62,"column":27},"source":"../node_modules/rc-select/es/util.js","original":{"line":33,"column":27}},{"name":"tags","generated":{"line":62,"column":33},"source":"../node_modules/rc-select/es/util.js","original":{"line":33,"column":33}},{"generated":{"line":62,"column":37},"source":"../node_modules/rc-select/es/util.js","original":{"line":33,"column":2}},{"generated":{"line":63,"column":0},"source":"../node_modules/rc-select/es/util.js","original":{"line":34,"column":1}},{"generated":{"line":65,"column":0},"source":"../node_modules/rc-select/es/util.js","original":{"line":36,"column":7}},{"name":"isMultipleOrTagsOrCombobox","generated":{"line":65,"column":9},"source":"../node_modules/rc-select/es/util.js","original":{"line":36,"column":16}},{"generated":{"line":65,"column":35},"source":"../node_modules/rc-select/es/util.js","original":{"line":36,"column":7}},{"name":"props","generated":{"line":65,"column":36},"source":"../node_modules/rc-select/es/util.js","original":{"line":36,"column":43}},{"generated":{"line":65,"column":41},"source":"../node_modules/rc-select/es/util.js","original":{"line":36,"column":7}},{"generated":{"line":65,"column":43},"source":"../node_modules/rc-select/es/util.js","original":{"line":36,"column":50}},{"generated":{"line":66,"column":0},"source":"../node_modules/rc-select/es/util.js","original":{"line":37,"column":2}},{"name":"isMultipleOrTags","generated":{"line":66,"column":9},"source":"../node_modules/rc-select/es/util.js","original":{"line":37,"column":9}},{"name":"props","generated":{"line":66,"column":26},"source":"../node_modules/rc-select/es/util.js","original":{"line":37,"column":26}},{"generated":{"line":66,"column":31},"source":"../node_modules/rc-select/es/util.js","original":{"line":37,"column":9}},{"name":"isCombobox","generated":{"line":66,"column":36},"source":"../node_modules/rc-select/es/util.js","original":{"line":37,"column":36}},{"name":"props","generated":{"line":66,"column":47},"source":"../node_modules/rc-select/es/util.js","original":{"line":37,"column":47}},{"generated":{"line":66,"column":52},"source":"../node_modules/rc-select/es/util.js","original":{"line":37,"column":36}},{"generated":{"line":66,"column":53},"source":"../node_modules/rc-select/es/util.js","original":{"line":37,"column":2}},{"generated":{"line":67,"column":0},"source":"../node_modules/rc-select/es/util.js","original":{"line":38,"column":1}},{"generated":{"line":69,"column":0},"source":"../node_modules/rc-select/es/util.js","original":{"line":40,"column":7}},{"name":"isSingleMode","generated":{"line":69,"column":9},"source":"../node_modules/rc-select/es/util.js","original":{"line":40,"column":16}},{"generated":{"line":69,"column":21},"source":"../node_modules/rc-select/es/util.js","original":{"line":40,"column":7}},{"name":"props","generated":{"line":69,"column":22},"source":"../node_modules/rc-select/es/util.js","original":{"line":40,"column":29}},{"generated":{"line":69,"column":27},"source":"../node_modules/rc-select/es/util.js","original":{"line":40,"column":7}},{"generated":{"line":69,"column":29},"source":"../node_modules/rc-select/es/util.js","original":{"line":40,"column":36}},{"generated":{"line":70,"column":0},"source":"../node_modules/rc-select/es/util.js","original":{"line":41,"column":2}},{"generated":{"line":70,"column":9},"source":"../node_modules/rc-select/es/util.js","original":{"line":41,"column":9}},{"name":"isMultipleOrTagsOrCombobox","generated":{"line":70,"column":10},"source":"../node_modules/rc-select/es/util.js","original":{"line":41,"column":10}},{"name":"props","generated":{"line":70,"column":37},"source":"../node_modules/rc-select/es/util.js","original":{"line":41,"column":37}},{"generated":{"line":70,"column":42},"source":"../node_modules/rc-select/es/util.js","original":{"line":41,"column":10}},{"generated":{"line":70,"column":43},"source":"../node_modules/rc-select/es/util.js","original":{"line":41,"column":2}},{"generated":{"line":71,"column":0},"source":"../node_modules/rc-select/es/util.js","original":{"line":42,"column":1}},{"generated":{"line":73,"column":0},"source":"../node_modules/rc-select/es/util.js","original":{"line":44,"column":7}},{"name":"toArray","generated":{"line":73,"column":9},"source":"../node_modules/rc-select/es/util.js","original":{"line":44,"column":16}},{"generated":{"line":73,"column":16},"source":"../node_modules/rc-select/es/util.js","original":{"line":44,"column":7}},{"name":"value","generated":{"line":73,"column":17},"source":"../node_modules/rc-select/es/util.js","original":{"line":44,"column":24}},{"generated":{"line":73,"column":22},"source":"../node_modules/rc-select/es/util.js","original":{"line":44,"column":7}},{"generated":{"line":73,"column":24},"source":"../node_modules/rc-select/es/util.js","original":{"line":44,"column":31}},{"generated":{"line":74,"column":0},"source":"../node_modules/rc-select/es/util.js","original":{"line":45,"column":2}},{"name":"ret","generated":{"line":74,"column":6},"source":"../node_modules/rc-select/es/util.js","original":{"line":45,"column":6}},{"name":"value","generated":{"line":74,"column":12},"source":"../node_modules/rc-select/es/util.js","original":{"line":45,"column":12}},{"generated":{"line":74,"column":17},"source":"../node_modules/rc-select/es/util.js","original":{"line":45,"column":2}},{"generated":{"line":75,"column":0},"source":"../node_modules/rc-select/es/util.js","original":{"line":46,"column":2}},{"name":"value","generated":{"line":75,"column":6},"source":"../node_modules/rc-select/es/util.js","original":{"line":46,"column":6}},{"name":"undefined","generated":{"line":75,"column":16},"source":"../node_modules/rc-select/es/util.js","original":{"line":46,"column":16}},{"generated":{"line":75,"column":25},"source":"../node_modules/rc-select/es/util.js","original":{"line":46,"column":2}},{"generated":{"line":75,"column":27},"source":"../node_modules/rc-select/es/util.js","original":{"line":46,"column":27}},{"name":"ret","generated":{"line":76,"column":0},"source":"../node_modules/rc-select/es/util.js","original":{"line":47,"column":4}},{"generated":{"line":76,"column":10},"source":"../node_modules/rc-select/es/util.js","original":{"line":47,"column":10}},{"generated":{"line":76,"column":12},"source":"../node_modules/rc-select/es/util.js","original":{"line":47,"column":4}},{"generated":{"line":77,"column":0},"source":"../node_modules/rc-select/es/util.js","original":{"line":48,"column":3}},{"generated":{"line":77,"column":3},"source":"../node_modules/rc-select/es/util.js","original":{"line":46,"column":2}},{"generated":{"line":77,"column":9},"source":"../node_modules/rc-select/es/util.js","original":{"line":48,"column":9}},{"generated":{"line":77,"column":13},"source":"../node_modules/rc-select/es/util.js","original":{"line":48,"column":13}},{"name":"Array","generated":{"line":77,"column":14},"source":"../node_modules/rc-select/es/util.js","original":{"line":48,"column":14}},{"name":"isArray","generated":{"line":77,"column":20},"source":"../node_modules/rc-select/es/util.js","original":{"line":48,"column":20}},{"generated":{"line":77,"column":27},"source":"../node_modules/rc-select/es/util.js","original":{"line":48,"column":14}},{"name":"value","generated":{"line":77,"column":28},"source":"../node_modules/rc-select/es/util.js","original":{"line":48,"column":28}},{"generated":{"line":77,"column":33},"source":"../node_modules/rc-select/es/util.js","original":{"line":48,"column":14}},{"generated":{"line":77,"column":34},"source":"../node_modules/rc-select/es/util.js","original":{"line":48,"column":9}},{"generated":{"line":77,"column":36},"source":"../node_modules/rc-select/es/util.js","original":{"line":48,"column":36}},{"name":"ret","generated":{"line":78,"column":0},"source":"../node_modules/rc-select/es/util.js","original":{"line":49,"column":4}},{"generated":{"line":78,"column":10},"source":"../node_modules/rc-select/es/util.js","original":{"line":49,"column":10}},{"name":"value","generated":{"line":78,"column":11},"source":"../node_modules/rc-select/es/util.js","original":{"line":49,"column":11}},{"generated":{"line":78,"column":16},"source":"../node_modules/rc-select/es/util.js","original":{"line":49,"column":10}},{"generated":{"line":78,"column":17},"source":"../node_modules/rc-select/es/util.js","original":{"line":49,"column":4}},{"generated":{"line":79,"column":0},"source":"../node_modules/rc-select/es/util.js","original":{"line":50,"column":3}},{"generated":{"line":80,"column":0},"source":"../node_modules/rc-select/es/util.js","original":{"line":51,"column":2}},{"name":"ret","generated":{"line":80,"column":9},"source":"../node_modules/rc-select/es/util.js","original":{"line":51,"column":9}},{"generated":{"line":80,"column":12},"source":"../node_modules/rc-select/es/util.js","original":{"line":51,"column":2}},{"generated":{"line":81,"column":0},"source":"../node_modules/rc-select/es/util.js","original":{"line":52,"column":1}},{"generated":{"line":83,"column":0},"source":"../node_modules/rc-select/es/util.js","original":{"line":54,"column":7}},{"name":"preventDefaultEvent","generated":{"line":83,"column":9},"source":"../node_modules/rc-select/es/util.js","original":{"line":54,"column":16}},{"generated":{"line":83,"column":28},"source":"../node_modules/rc-select/es/util.js","original":{"line":54,"column":7}},{"name":"e","generated":{"line":83,"column":29},"source":"../node_modules/rc-select/es/util.js","original":{"line":54,"column":36}},{"generated":{"line":83,"column":30},"source":"../node_modules/rc-select/es/util.js","original":{"line":54,"column":7}},{"generated":{"line":83,"column":32},"source":"../node_modules/rc-select/es/util.js","original":{"line":54,"column":39}},{"name":"e","generated":{"line":84,"column":0},"source":"../node_modules/rc-select/es/util.js","original":{"line":55,"column":2}},{"name":"preventDefault","generated":{"line":84,"column":4},"source":"../node_modules/rc-select/es/util.js","original":{"line":55,"column":4}},{"generated":{"line":84,"column":18},"source":"../node_modules/rc-select/es/util.js","original":{"line":55,"column":2}},{"generated":{"line":85,"column":0},"source":"../node_modules/rc-select/es/util.js","original":{"line":56,"column":1}},{"generated":{"line":87,"column":0},"source":"../node_modules/rc-select/es/util.js","original":{"line":58,"column":7}},{"name":"findIndexInValueByKey","generated":{"line":87,"column":9},"source":"../node_modules/rc-select/es/util.js","original":{"line":58,"column":16}},{"generated":{"line":87,"column":30},"source":"../node_modules/rc-select/es/util.js","original":{"line":58,"column":7}},{"name":"value","generated":{"line":87,"column":31},"source":"../node_modules/rc-select/es/util.js","original":{"line":58,"column":38}},{"generated":{"line":87,"column":36},"source":"../node_modules/rc-select/es/util.js","original":{"line":58,"column":7}},{"name":"key","generated":{"line":87,"column":38},"source":"../node_modules/rc-select/es/util.js","original":{"line":58,"column":45}},{"generated":{"line":87,"column":41},"source":"../node_modules/rc-select/es/util.js","original":{"line":58,"column":7}},{"generated":{"line":87,"column":43},"source":"../node_modules/rc-select/es/util.js","original":{"line":58,"column":50}},{"generated":{"line":88,"column":0},"source":"../node_modules/rc-select/es/util.js","original":{"line":59,"column":2}},{"name":"index","generated":{"line":88,"column":6},"source":"../node_modules/rc-select/es/util.js","original":{"line":59,"column":6}},{"generated":{"line":88,"column":14},"source":"../node_modules/rc-select/es/util.js","original":{"line":59,"column":14}},{"generated":{"line":88,"column":15},"source":"../node_modules/rc-select/es/util.js","original":{"line":59,"column":15}},{"generated":{"line":88,"column":16},"source":"../node_modules/rc-select/es/util.js","original":{"line":59,"column":2}},{"generated":{"line":89,"column":0},"source":"../node_modules/rc-select/es/util.js","original":{"line":60,"column":2}},{"generated":{"line":89,"column":7},"source":"../node_modules/rc-select/es/util.js","original":{"line":60,"column":7}},{"name":"i","generated":{"line":89,"column":11},"source":"../node_modules/rc-select/es/util.js","original":{"line":60,"column":11}},{"generated":{"line":89,"column":15},"source":"../node_modules/rc-select/es/util.js","original":{"line":60,"column":15}},{"generated":{"line":89,"column":16},"source":"../node_modules/rc-select/es/util.js","original":{"line":60,"column":2}},{"name":"i","generated":{"line":89,"column":18},"source":"../node_modules/rc-select/es/util.js","original":{"line":60,"column":18}},{"name":"value","generated":{"line":89,"column":22},"source":"../node_modules/rc-select/es/util.js","original":{"line":60,"column":22}},{"name":"length","generated":{"line":89,"column":28},"source":"../node_modules/rc-select/es/util.js","original":{"line":60,"column":28}},{"generated":{"line":89,"column":34},"source":"../node_modules/rc-select/es/util.js","original":{"line":60,"column":2}},{"name":"i","generated":{"line":89,"column":36},"source":"../node_modules/rc-select/es/util.js","original":{"line":60,"column":36}},{"generated":{"line":89,"column":39},"source":"../node_modules/rc-select/es/util.js","original":{"line":60,"column":2}},{"generated":{"line":89,"column":41},"source":"../node_modules/rc-select/es/util.js","original":{"line":60,"column":41}},{"generated":{"line":90,"column":0},"source":"../node_modules/rc-select/es/util.js","original":{"line":61,"column":4}},{"name":"value","generated":{"line":90,"column":8},"source":"../node_modules/rc-select/es/util.js","original":{"line":61,"column":8}},{"name":"i","generated":{"line":90,"column":14},"source":"../node_modules/rc-select/es/util.js","original":{"line":61,"column":14}},{"generated":{"line":90,"column":15},"source":"../node_modules/rc-select/es/util.js","original":{"line":61,"column":8}},{"name":"key","generated":{"line":90,"column":17},"source":"../node_modules/rc-select/es/util.js","original":{"line":61,"column":17}},{"generated":{"line":90,"column":20},"source":"../node_modules/rc-select/es/util.js","original":{"line":61,"column":8}},{"name":"key","generated":{"line":90,"column":25},"source":"../node_modules/rc-select/es/util.js","original":{"line":61,"column":25}},{"generated":{"line":90,"column":28},"source":"../node_modules/rc-select/es/util.js","original":{"line":61,"column":4}},{"generated":{"line":90,"column":30},"source":"../node_modules/rc-select/es/util.js","original":{"line":61,"column":30}},{"name":"index","generated":{"line":91,"column":0},"source":"../node_modules/rc-select/es/util.js","original":{"line":62,"column":6}},{"name":"i","generated":{"line":91,"column":14},"source":"../node_modules/rc-select/es/util.js","original":{"line":62,"column":14}},{"generated":{"line":91,"column":15},"source":"../node_modules/rc-select/es/util.js","original":{"line":62,"column":6}},{"generated":{"line":92,"column":0},"source":"../node_modules/rc-select/es/util.js","original":{"line":63,"column":6}},{"generated":{"line":93,"column":0},"source":"../node_modules/rc-select/es/util.js","original":{"line":64,"column":5}},{"generated":{"line":94,"column":0},"source":"../node_modules/rc-select/es/util.js","original":{"line":65,"column":3}},{"generated":{"line":95,"column":0},"source":"../node_modules/rc-select/es/util.js","original":{"line":66,"column":2}},{"name":"index","generated":{"line":95,"column":9},"source":"../node_modules/rc-select/es/util.js","original":{"line":66,"column":9}},{"generated":{"line":95,"column":14},"source":"../node_modules/rc-select/es/util.js","original":{"line":66,"column":2}},{"generated":{"line":96,"column":0},"source":"../node_modules/rc-select/es/util.js","original":{"line":67,"column":1}},{"generated":{"line":98,"column":0},"source":"../node_modules/rc-select/es/util.js","original":{"line":69,"column":7}},{"name":"findIndexInValueByLabel","generated":{"line":98,"column":9},"source":"../node_modules/rc-select/es/util.js","original":{"line":69,"column":16}},{"generated":{"line":98,"column":32},"source":"../node_modules/rc-select/es/util.js","original":{"line":69,"column":7}},{"name":"value","generated":{"line":98,"column":33},"source":"../node_modules/rc-select/es/util.js","original":{"line":69,"column":40}},{"generated":{"line":98,"column":38},"source":"../node_modules/rc-select/es/util.js","original":{"line":69,"column":7}},{"name":"label","generated":{"line":98,"column":40},"source":"../node_modules/rc-select/es/util.js","original":{"line":69,"column":47}},{"generated":{"line":98,"column":45},"source":"../node_modules/rc-select/es/util.js","original":{"line":69,"column":7}},{"generated":{"line":98,"column":47},"source":"../node_modules/rc-select/es/util.js","original":{"line":69,"column":54}},{"generated":{"line":99,"column":0},"source":"../node_modules/rc-select/es/util.js","original":{"line":70,"column":2}},{"name":"index","generated":{"line":99,"column":6},"source":"../node_modules/rc-select/es/util.js","original":{"line":70,"column":6}},{"generated":{"line":99,"column":14},"source":"../node_modules/rc-select/es/util.js","original":{"line":70,"column":14}},{"generated":{"line":99,"column":15},"source":"../node_modules/rc-select/es/util.js","original":{"line":70,"column":15}},{"generated":{"line":99,"column":16},"source":"../node_modules/rc-select/es/util.js","original":{"line":70,"column":2}},{"generated":{"line":100,"column":0},"source":"../node_modules/rc-select/es/util.js","original":{"line":71,"column":2}},{"generated":{"line":100,"column":7},"source":"../node_modules/rc-select/es/util.js","original":{"line":71,"column":7}},{"name":"i","generated":{"line":100,"column":11},"source":"../node_modules/rc-select/es/util.js","original":{"line":71,"column":11}},{"generated":{"line":100,"column":15},"source":"../node_modules/rc-select/es/util.js","original":{"line":71,"column":15}},{"generated":{"line":100,"column":16},"source":"../node_modules/rc-select/es/util.js","original":{"line":71,"column":2}},{"name":"i","generated":{"line":100,"column":18},"source":"../node_modules/rc-select/es/util.js","original":{"line":71,"column":18}},{"name":"value","generated":{"line":100,"column":22},"source":"../node_modules/rc-select/es/util.js","original":{"line":71,"column":22}},{"name":"length","generated":{"line":100,"column":28},"source":"../node_modules/rc-select/es/util.js","original":{"line":71,"column":28}},{"generated":{"line":100,"column":34},"source":"../node_modules/rc-select/es/util.js","original":{"line":71,"column":2}},{"name":"i","generated":{"line":100,"column":36},"source":"../node_modules/rc-select/es/util.js","original":{"line":71,"column":36}},{"generated":{"line":100,"column":39},"source":"../node_modules/rc-select/es/util.js","original":{"line":71,"column":2}},{"generated":{"line":100,"column":41},"source":"../node_modules/rc-select/es/util.js","original":{"line":71,"column":41}},{"generated":{"line":101,"column":0},"source":"../node_modules/rc-select/es/util.js","original":{"line":72,"column":4}},{"name":"toArray","generated":{"line":101,"column":8},"source":"../node_modules/rc-select/es/util.js","original":{"line":72,"column":8}},{"name":"value","generated":{"line":101,"column":16},"source":"../node_modules/rc-select/es/util.js","original":{"line":72,"column":16}},{"name":"i","generated":{"line":101,"column":22},"source":"../node_modules/rc-select/es/util.js","original":{"line":72,"column":22}},{"generated":{"line":101,"column":23},"source":"../node_modules/rc-select/es/util.js","original":{"line":72,"column":16}},{"name":"label","generated":{"line":101,"column":25},"source":"../node_modules/rc-select/es/util.js","original":{"line":72,"column":25}},{"generated":{"line":101,"column":30},"source":"../node_modules/rc-select/es/util.js","original":{"line":72,"column":8}},{"name":"join","generated":{"line":101,"column":32},"source":"../node_modules/rc-select/es/util.js","original":{"line":72,"column":32}},{"generated":{"line":101,"column":36},"source":"../node_modules/rc-select/es/util.js","original":{"line":72,"column":8}},{"generated":{"line":101,"column":37},"source":"../node_modules/rc-select/es/util.js","original":{"line":72,"column":37}},{"generated":{"line":101,"column":39},"source":"../node_modules/rc-select/es/util.js","original":{"line":72,"column":8}},{"name":"label","generated":{"line":101,"column":45},"source":"../node_modules/rc-select/es/util.js","original":{"line":72,"column":45}},{"generated":{"line":101,"column":50},"source":"../node_modules/rc-select/es/util.js","original":{"line":72,"column":4}},{"generated":{"line":101,"column":52},"source":"../node_modules/rc-select/es/util.js","original":{"line":72,"column":52}},{"name":"index","generated":{"line":102,"column":0},"source":"../node_modules/rc-select/es/util.js","original":{"line":73,"column":6}},{"name":"i","generated":{"line":102,"column":14},"source":"../node_modules/rc-select/es/util.js","original":{"line":73,"column":14}},{"generated":{"line":102,"column":15},"source":"../node_modules/rc-select/es/util.js","original":{"line":73,"column":6}},{"generated":{"line":103,"column":0},"source":"../node_modules/rc-select/es/util.js","original":{"line":74,"column":6}},{"generated":{"line":104,"column":0},"source":"../node_modules/rc-select/es/util.js","original":{"line":75,"column":5}},{"generated":{"line":105,"column":0},"source":"../node_modules/rc-select/es/util.js","original":{"line":76,"column":3}},{"generated":{"line":106,"column":0},"source":"../node_modules/rc-select/es/util.js","original":{"line":77,"column":2}},{"name":"index","generated":{"line":106,"column":9},"source":"../node_modules/rc-select/es/util.js","original":{"line":77,"column":9}},{"generated":{"line":106,"column":14},"source":"../node_modules/rc-select/es/util.js","original":{"line":77,"column":2}},{"generated":{"line":107,"column":0},"source":"../node_modules/rc-select/es/util.js","original":{"line":78,"column":1}},{"generated":{"line":109,"column":0},"source":"../node_modules/rc-select/es/util.js","original":{"line":80,"column":7}},{"name":"getSelectKeys","generated":{"line":109,"column":9},"source":"../node_modules/rc-select/es/util.js","original":{"line":80,"column":16}},{"generated":{"line":109,"column":22},"source":"../node_modules/rc-select/es/util.js","original":{"line":80,"column":7}},{"name":"menuItems","generated":{"line":109,"column":23},"source":"../node_modules/rc-select/es/util.js","original":{"line":80,"column":30}},{"generated":{"line":109,"column":32},"source":"../node_modules/rc-select/es/util.js","original":{"line":80,"column":7}},{"name":"value","generated":{"line":109,"column":34},"source":"../node_modules/rc-select/es/util.js","original":{"line":80,"column":41}},{"generated":{"line":109,"column":39},"source":"../node_modules/rc-select/es/util.js","original":{"line":80,"column":7}},{"generated":{"line":109,"column":41},"source":"../node_modules/rc-select/es/util.js","original":{"line":80,"column":48}},{"generated":{"line":110,"column":0},"source":"../node_modules/rc-select/es/util.js","original":{"line":81,"column":2}},{"name":"value","generated":{"line":110,"column":6},"source":"../node_modules/rc-select/es/util.js","original":{"line":81,"column":6}},{"generated":{"line":110,"column":16},"source":"../node_modules/rc-select/es/util.js","original":{"line":81,"column":16}},{"generated":{"line":110,"column":20},"source":"../node_modules/rc-select/es/util.js","original":{"line":81,"column":6}},{"name":"value","generated":{"line":110,"column":24},"source":"../node_modules/rc-select/es/util.js","original":{"line":81,"column":24}},{"name":"undefined","generated":{"line":110,"column":34},"source":"../node_modules/rc-select/es/util.js","original":{"line":81,"column":34}},{"generated":{"line":110,"column":43},"source":"../node_modules/rc-select/es/util.js","original":{"line":81,"column":2}},{"generated":{"line":110,"column":45},"source":"../node_modules/rc-select/es/util.js","original":{"line":81,"column":45}},{"generated":{"line":111,"column":0},"source":"../node_modules/rc-select/es/util.js","original":{"line":82,"column":4}},{"generated":{"line":111,"column":11},"source":"../node_modules/rc-select/es/util.js","original":{"line":82,"column":11}},{"generated":{"line":111,"column":13},"source":"../node_modules/rc-select/es/util.js","original":{"line":82,"column":4}},{"generated":{"line":112,"column":0},"source":"../node_modules/rc-select/es/util.js","original":{"line":83,"column":3}},{"generated":{"line":113,"column":0},"source":"../node_modules/rc-select/es/util.js","original":{"line":84,"column":2}},{"name":"selectedKeys","generated":{"line":113,"column":6},"source":"../node_modules/rc-select/es/util.js","original":{"line":84,"column":6}},{"generated":{"line":113,"column":21},"source":"../node_modules/rc-select/es/util.js","original":{"line":84,"column":21}},{"generated":{"line":113,"column":23},"source":"../node_modules/rc-select/es/util.js","original":{"line":84,"column":2}},{"name":"React","generated":{"line":114,"column":0},"source":"../node_modules/rc-select/es/util.js","original":{"line":85,"column":2}},{"name":"Children","generated":{"line":114,"column":18},"source":"../node_modules/rc-select/es/util.js","original":{"line":85,"column":8}},{"generated":{"line":114,"column":26},"source":"../node_modules/rc-select/es/util.js","original":{"line":85,"column":2}},{"name":"forEach","generated":{"line":114,"column":27},"source":"../node_modules/rc-select/es/util.js","original":{"line":85,"column":17}},{"generated":{"line":114,"column":34},"source":"../node_modules/rc-select/es/util.js","original":{"line":85,"column":2}},{"name":"menuItems","generated":{"line":114,"column":35},"source":"../node_modules/rc-select/es/util.js","original":{"line":85,"column":25}},{"generated":{"line":114,"column":44},"source":"../node_modules/rc-select/es/util.js","original":{"line":85,"column":2}},{"generated":{"line":114,"column":46},"source":"../node_modules/rc-select/es/util.js","original":{"line":85,"column":36}},{"name":"item","generated":{"line":114,"column":56},"source":"../node_modules/rc-select/es/util.js","original":{"line":85,"column":46}},{"generated":{"line":114,"column":60},"source":"../node_modules/rc-select/es/util.js","original":{"line":85,"column":36}},{"generated":{"line":114,"column":62},"source":"../node_modules/rc-select/es/util.js","original":{"line":85,"column":52}},{"generated":{"line":115,"column":0},"source":"../node_modules/rc-select/es/util.js","original":{"line":86,"column":4}},{"name":"item","generated":{"line":115,"column":8},"source":"../node_modules/rc-select/es/util.js","original":{"line":86,"column":8}},{"name":"type","generated":{"line":115,"column":13},"source":"../node_modules/rc-select/es/util.js","original":{"line":86,"column":13}},{"generated":{"line":115,"column":17},"source":"../node_modules/rc-select/es/util.js","original":{"line":86,"column":8}},{"name":"isMenuItemGroup","generated":{"line":115,"column":18},"source":"../node_modules/rc-select/es/util.js","original":{"line":86,"column":18}},{"generated":{"line":115,"column":33},"source":"../node_modules/rc-select/es/util.js","original":{"line":86,"column":4}},{"generated":{"line":115,"column":35},"source":"../node_modules/rc-select/es/util.js","original":{"line":86,"column":35}},{"name":"selectedKeys","generated":{"line":116,"column":0},"source":"../node_modules/rc-select/es/util.js","original":{"line":87,"column":6}},{"name":"selectedKeys","generated":{"line":116,"column":21},"source":"../node_modules/rc-select/es/util.js","original":{"line":87,"column":21}},{"name":"concat","generated":{"line":116,"column":34},"source":"../node_modules/rc-select/es/util.js","original":{"line":87,"column":34}},{"generated":{"line":116,"column":40},"source":"../node_modules/rc-select/es/util.js","original":{"line":87,"column":21}},{"name":"getSelectKeys","generated":{"line":116,"column":41},"source":"../node_modules/rc-select/es/util.js","original":{"line":87,"column":41}},{"name":"item","generated":{"line":116,"column":55},"source":"../node_modules/rc-select/es/util.js","original":{"line":87,"column":55}},{"name":"props","generated":{"line":116,"column":60},"source":"../node_modules/rc-select/es/util.js","original":{"line":87,"column":60}},{"generated":{"line":116,"column":65},"source":"../node_modules/rc-select/es/util.js","original":{"line":87,"column":55}},{"name":"children","generated":{"line":116,"column":66},"source":"../node_modules/rc-select/es/util.js","original":{"line":87,"column":66}},{"generated":{"line":116,"column":74},"source":"../node_modules/rc-select/es/util.js","original":{"line":87,"column":41}},{"name":"value","generated":{"line":116,"column":76},"source":"../node_modules/rc-select/es/util.js","original":{"line":87,"column":76}},{"generated":{"line":116,"column":81},"source":"../node_modules/rc-select/es/util.js","original":{"line":87,"column":41}},{"generated":{"line":116,"column":82},"source":"../node_modules/rc-select/es/util.js","original":{"line":87,"column":21}},{"generated":{"line":116,"column":83},"source":"../node_modules/rc-select/es/util.js","original":{"line":87,"column":6}},{"generated":{"line":117,"column":0},"source":"../node_modules/rc-select/es/util.js","original":{"line":88,"column":5}},{"generated":{"line":117,"column":5},"source":"../node_modules/rc-select/es/util.js","original":{"line":86,"column":4}},{"generated":{"line":117,"column":11},"source":"../node_modules/rc-select/es/util.js","original":{"line":88,"column":11}},{"generated":{"line":118,"column":0},"source":"../node_modules/rc-select/es/util.js","original":{"line":89,"column":6}},{"name":"itemValue","generated":{"line":118,"column":10},"source":"../node_modules/rc-select/es/util.js","original":{"line":89,"column":10}},{"name":"getValuePropValue","generated":{"line":118,"column":22},"source":"../node_modules/rc-select/es/util.js","original":{"line":89,"column":22}},{"name":"item","generated":{"line":118,"column":40},"source":"../node_modules/rc-select/es/util.js","original":{"line":89,"column":40}},{"generated":{"line":118,"column":44},"source":"../node_modules/rc-select/es/util.js","original":{"line":89,"column":22}},{"generated":{"line":118,"column":45},"source":"../node_modules/rc-select/es/util.js","original":{"line":89,"column":6}},{"generated":{"line":119,"column":0},"source":"../node_modules/rc-select/es/util.js","original":{"line":90,"column":6}},{"name":"itemKey","generated":{"line":119,"column":10},"source":"../node_modules/rc-select/es/util.js","original":{"line":90,"column":10}},{"name":"item","generated":{"line":119,"column":20},"source":"../node_modules/rc-select/es/util.js","original":{"line":90,"column":20}},{"name":"key","generated":{"line":119,"column":25},"source":"../node_modules/rc-select/es/util.js","original":{"line":90,"column":25}},{"generated":{"line":119,"column":28},"source":"../node_modules/rc-select/es/util.js","original":{"line":90,"column":6}},{"generated":{"line":120,"column":0},"source":"../node_modules/rc-select/es/util.js","original":{"line":91,"column":6}},{"name":"findIndexInValueByKey","generated":{"line":120,"column":10},"source":"../node_modules/rc-select/es/util.js","original":{"line":91,"column":10}},{"name":"value","generated":{"line":120,"column":32},"source":"../node_modules/rc-select/es/util.js","original":{"line":91,"column":32}},{"generated":{"line":120,"column":37},"source":"../node_modules/rc-select/es/util.js","original":{"line":91,"column":10}},{"name":"itemValue","generated":{"line":120,"column":39},"source":"../node_modules/rc-select/es/util.js","original":{"line":91,"column":39}},{"generated":{"line":120,"column":48},"source":"../node_modules/rc-select/es/util.js","original":{"line":91,"column":10}},{"generated":{"line":120,"column":54},"source":"../node_modules/rc-select/es/util.js","original":{"line":91,"column":54}},{"generated":{"line":120,"column":55},"source":"../node_modules/rc-select/es/util.js","original":{"line":91,"column":55}},{"generated":{"line":120,"column":56},"source":"../node_modules/rc-select/es/util.js","original":{"line":91,"column":10}},{"name":"itemKey","generated":{"line":120,"column":60},"source":"../node_modules/rc-select/es/util.js","original":{"line":91,"column":60}},{"generated":{"line":120,"column":67},"source":"../node_modules/rc-select/es/util.js","original":{"line":91,"column":6}},{"generated":{"line":120,"column":69},"source":"../node_modules/rc-select/es/util.js","original":{"line":91,"column":69}},{"name":"selectedKeys","generated":{"line":121,"column":0},"source":"../node_modules/rc-select/es/util.js","original":{"line":92,"column":8}},{"name":"push","generated":{"line":121,"column":21},"source":"../node_modules/rc-select/es/util.js","original":{"line":92,"column":21}},{"generated":{"line":121,"column":25},"source":"../node_modules/rc-select/es/util.js","original":{"line":92,"column":8}},{"name":"itemKey","generated":{"line":121,"column":26},"source":"../node_modules/rc-select/es/util.js","original":{"line":92,"column":26}},{"generated":{"line":121,"column":33},"source":"../node_modules/rc-select/es/util.js","original":{"line":92,"column":8}},{"generated":{"line":122,"column":0},"source":"../node_modules/rc-select/es/util.js","original":{"line":93,"column":7}},{"generated":{"line":123,"column":0},"source":"../node_modules/rc-select/es/util.js","original":{"line":94,"column":5}},{"generated":{"line":124,"column":0},"source":"../node_modules/rc-select/es/util.js","original":{"line":95,"column":3}},{"generated":{"line":124,"column":3},"source":"../node_modules/rc-select/es/util.js","original":{"line":85,"column":2}},{"generated":{"line":125,"column":0},"source":"../node_modules/rc-select/es/util.js","original":{"line":96,"column":2}},{"name":"selectedKeys","generated":{"line":125,"column":9},"source":"../node_modules/rc-select/es/util.js","original":{"line":96,"column":9}},{"generated":{"line":125,"column":21},"source":"../node_modules/rc-select/es/util.js","original":{"line":96,"column":2}},{"generated":{"line":126,"column":0},"source":"../node_modules/rc-select/es/util.js","original":{"line":97,"column":1}},{"generated":{"line":128,"column":0},"source":"../node_modules/rc-select/es/util.js","original":{"line":99,"column":7}},{"name":"UNSELECTABLE_STYLE","generated":{"line":128,"column":4},"source":"../node_modules/rc-select/es/util.js","original":{"line":99,"column":11}},{"generated":{"line":128,"column":54},"source":"../node_modules/rc-select/es/util.js","original":{"line":99,"column":32}},{"name":"userSelect","generated":{"line":129,"column":0},"source":"../node_modules/rc-select/es/util.js","original":{"line":100,"column":2}},{"generated":{"line":129,"column":14},"source":"../node_modules/rc-select/es/util.js","original":{"line":100,"column":14}},{"generated":{"line":129,"column":20},"source":"../node_modules/rc-select/es/util.js","original":{"line":99,"column":32}},{"name":"WebkitUserSelect","generated":{"line":130,"column":0},"source":"../node_modules/rc-select/es/util.js","original":{"line":101,"column":2}},{"generated":{"line":130,"column":20},"source":"../node_modules/rc-select/es/util.js","original":{"line":101,"column":20}},{"generated":{"line":131,"column":0},"source":"../node_modules/rc-select/es/util.js","original":{"line":99,"column":32}},{"generated":{"line":131,"column":1},"source":"../node_modules/rc-select/es/util.js","original":{"line":99,"column":7}},{"generated":{"line":133,"column":0},"source":"../node_modules/rc-select/es/util.js","original":{"line":104,"column":7}},{"name":"UNSELECTABLE_ATTRIBUTE","generated":{"line":133,"column":4},"source":"../node_modules/rc-select/es/util.js","original":{"line":104,"column":11}},{"generated":{"line":133,"column":62},"source":"../node_modules/rc-select/es/util.js","original":{"line":104,"column":36}},{"name":"unselectable","generated":{"line":134,"column":0},"source":"../node_modules/rc-select/es/util.js","original":{"line":105,"column":2}},{"generated":{"line":134,"column":16},"source":"../node_modules/rc-select/es/util.js","original":{"line":105,"column":16}},{"generated":{"line":135,"column":0},"source":"../node_modules/rc-select/es/util.js","original":{"line":104,"column":36}},{"generated":{"line":135,"column":1},"source":"../node_modules/rc-select/es/util.js","original":{"line":104,"column":7}},{"generated":{"line":137,"column":0},"source":"../node_modules/rc-select/es/util.js","original":{"line":108,"column":7}},{"name":"findFirstMenuItem","generated":{"line":137,"column":9},"source":"../node_modules/rc-select/es/util.js","original":{"line":108,"column":16}},{"generated":{"line":137,"column":26},"source":"../node_modules/rc-select/es/util.js","original":{"line":108,"column":7}},{"name":"children","generated":{"line":137,"column":27},"source":"../node_modules/rc-select/es/util.js","original":{"line":108,"column":34}},{"generated":{"line":137,"column":35},"source":"../node_modules/rc-select/es/util.js","original":{"line":108,"column":7}},{"generated":{"line":137,"column":37},"source":"../node_modules/rc-select/es/util.js","original":{"line":108,"column":44}},{"generated":{"line":138,"column":0},"source":"../node_modules/rc-select/es/util.js","original":{"line":109,"column":2}},{"generated":{"line":138,"column":7},"source":"../node_modules/rc-select/es/util.js","original":{"line":109,"column":7}},{"name":"i","generated":{"line":138,"column":11},"source":"../node_modules/rc-select/es/util.js","original":{"line":109,"column":11}},{"generated":{"line":138,"column":15},"source":"../node_modules/rc-select/es/util.js","original":{"line":109,"column":15}},{"generated":{"line":138,"column":16},"source":"../node_modules/rc-select/es/util.js","original":{"line":109,"column":2}},{"name":"i","generated":{"line":138,"column":18},"source":"../node_modules/rc-select/es/util.js","original":{"line":109,"column":18}},{"name":"children","generated":{"line":138,"column":22},"source":"../node_modules/rc-select/es/util.js","original":{"line":109,"column":22}},{"name":"length","generated":{"line":138,"column":31},"source":"../node_modules/rc-select/es/util.js","original":{"line":109,"column":31}},{"generated":{"line":138,"column":37},"source":"../node_modules/rc-select/es/util.js","original":{"line":109,"column":2}},{"name":"i","generated":{"line":138,"column":39},"source":"../node_modules/rc-select/es/util.js","original":{"line":109,"column":39}},{"generated":{"line":138,"column":42},"source":"../node_modules/rc-select/es/util.js","original":{"line":109,"column":2}},{"generated":{"line":138,"column":44},"source":"../node_modules/rc-select/es/util.js","original":{"line":109,"column":44}},{"generated":{"line":139,"column":0},"source":"../node_modules/rc-select/es/util.js","original":{"line":110,"column":4}},{"name":"child","generated":{"line":139,"column":8},"source":"../node_modules/rc-select/es/util.js","original":{"line":110,"column":8}},{"name":"children","generated":{"line":139,"column":16},"source":"../node_modules/rc-select/es/util.js","original":{"line":110,"column":16}},{"name":"i","generated":{"line":139,"column":25},"source":"../node_modules/rc-select/es/util.js","original":{"line":110,"column":25}},{"generated":{"line":139,"column":26},"source":"../node_modules/rc-select/es/util.js","original":{"line":110,"column":16}},{"generated":{"line":139,"column":27},"source":"../node_modules/rc-select/es/util.js","original":{"line":110,"column":4}},{"generated":{"line":140,"column":0},"source":"../node_modules/rc-select/es/util.js","original":{"line":111,"column":4}},{"name":"child","generated":{"line":140,"column":8},"source":"../node_modules/rc-select/es/util.js","original":{"line":111,"column":8}},{"name":"type","generated":{"line":140,"column":14},"source":"../node_modules/rc-select/es/util.js","original":{"line":111,"column":14}},{"generated":{"line":140,"column":18},"source":"../node_modules/rc-select/es/util.js","original":{"line":111,"column":8}},{"name":"isMenuItemGroup","generated":{"line":140,"column":19},"source":"../node_modules/rc-select/es/util.js","original":{"line":111,"column":19}},{"generated":{"line":140,"column":34},"source":"../node_modules/rc-select/es/util.js","original":{"line":111,"column":4}},{"generated":{"line":140,"column":36},"source":"../node_modules/rc-select/es/util.js","original":{"line":111,"column":36}},{"generated":{"line":141,"column":0},"source":"../node_modules/rc-select/es/util.js","original":{"line":112,"column":6}},{"name":"found","generated":{"line":141,"column":10},"source":"../node_modules/rc-select/es/util.js","original":{"line":112,"column":10}},{"name":"findFirstMenuItem","generated":{"line":141,"column":18},"source":"../node_modules/rc-select/es/util.js","original":{"line":112,"column":18}},{"name":"child","generated":{"line":141,"column":36},"source":"../node_modules/rc-select/es/util.js","original":{"line":112,"column":36}},{"name":"props","generated":{"line":141,"column":42},"source":"../node_modules/rc-select/es/util.js","original":{"line":112,"column":42}},{"generated":{"line":141,"column":47},"source":"../node_modules/rc-select/es/util.js","original":{"line":112,"column":36}},{"name":"children","generated":{"line":141,"column":48},"source":"../node_modules/rc-select/es/util.js","original":{"line":112,"column":48}},{"generated":{"line":141,"column":56},"source":"../node_modules/rc-select/es/util.js","original":{"line":112,"column":18}},{"generated":{"line":141,"column":57},"source":"../node_modules/rc-select/es/util.js","original":{"line":112,"column":6}},{"generated":{"line":142,"column":0},"source":"../node_modules/rc-select/es/util.js","original":{"line":113,"column":6}},{"name":"found","generated":{"line":142,"column":10},"source":"../node_modules/rc-select/es/util.js","original":{"line":113,"column":10}},{"generated":{"line":142,"column":15},"source":"../node_modules/rc-select/es/util.js","original":{"line":113,"column":6}},{"generated":{"line":142,"column":17},"source":"../node_modules/rc-select/es/util.js","original":{"line":113,"column":17}},{"generated":{"line":143,"column":0},"source":"../node_modules/rc-select/es/util.js","original":{"line":114,"column":8}},{"name":"found","generated":{"line":143,"column":15},"source":"../node_modules/rc-select/es/util.js","original":{"line":114,"column":15}},{"generated":{"line":143,"column":20},"source":"../node_modules/rc-select/es/util.js","original":{"line":114,"column":8}},{"generated":{"line":144,"column":0},"source":"../node_modules/rc-select/es/util.js","original":{"line":115,"column":7}},{"generated":{"line":145,"column":0},"source":"../node_modules/rc-select/es/util.js","original":{"line":116,"column":5}},{"generated":{"line":145,"column":5},"source":"../node_modules/rc-select/es/util.js","original":{"line":111,"column":4}},{"generated":{"line":145,"column":11},"source":"../node_modules/rc-select/es/util.js","original":{"line":116,"column":11}},{"generated":{"line":145,"column":15},"source":"../node_modules/rc-select/es/util.js","original":{"line":116,"column":15}},{"name":"child","generated":{"line":145,"column":16},"source":"../node_modules/rc-select/es/util.js","original":{"line":116,"column":16}},{"name":"props","generated":{"line":145,"column":22},"source":"../node_modules/rc-select/es/util.js","original":{"line":116,"column":22}},{"generated":{"line":145,"column":27},"source":"../node_modules/rc-select/es/util.js","original":{"line":116,"column":16}},{"name":"disabled","generated":{"line":145,"column":28},"source":"../node_modules/rc-select/es/util.js","original":{"line":116,"column":28}},{"generated":{"line":145,"column":36},"source":"../node_modules/rc-select/es/util.js","original":{"line":116,"column":11}},{"generated":{"line":145,"column":38},"source":"../node_modules/rc-select/es/util.js","original":{"line":116,"column":38}},{"generated":{"line":146,"column":0},"source":"../node_modules/rc-select/es/util.js","original":{"line":117,"column":6}},{"name":"child","generated":{"line":146,"column":13},"source":"../node_modules/rc-select/es/util.js","original":{"line":117,"column":13}},{"generated":{"line":146,"column":18},"source":"../node_modules/rc-select/es/util.js","original":{"line":117,"column":6}},{"generated":{"line":147,"column":0},"source":"../node_modules/rc-select/es/util.js","original":{"line":118,"column":5}},{"generated":{"line":148,"column":0},"source":"../node_modules/rc-select/es/util.js","original":{"line":119,"column":3}},{"generated":{"line":149,"column":0},"source":"../node_modules/rc-select/es/util.js","original":{"line":120,"column":2}},{"generated":{"line":149,"column":9},"source":"../node_modules/rc-select/es/util.js","original":{"line":120,"column":9}},{"generated":{"line":149,"column":13},"source":"../node_modules/rc-select/es/util.js","original":{"line":120,"column":2}},{"generated":{"line":150,"column":0},"source":"../node_modules/rc-select/es/util.js","original":{"line":121,"column":1}},{"generated":{"line":152,"column":0},"source":"../node_modules/rc-select/es/util.js","original":{"line":123,"column":7}},{"name":"includesSeparators","generated":{"line":152,"column":9},"source":"../node_modules/rc-select/es/util.js","original":{"line":123,"column":16}},{"generated":{"line":152,"column":27},"source":"../node_modules/rc-select/es/util.js","original":{"line":123,"column":7}},{"name":"string","generated":{"line":152,"column":28},"source":"../node_modules/rc-select/es/util.js","original":{"line":123,"column":35}},{"generated":{"line":152,"column":34},"source":"../node_modules/rc-select/es/util.js","original":{"line":123,"column":7}},{"name":"separators","generated":{"line":152,"column":36},"source":"../node_modules/rc-select/es/util.js","original":{"line":123,"column":43}},{"generated":{"line":152,"column":46},"source":"../node_modules/rc-select/es/util.js","original":{"line":123,"column":7}},{"generated":{"line":152,"column":48},"source":"../node_modules/rc-select/es/util.js","original":{"line":123,"column":55}},{"generated":{"line":153,"column":0},"source":"../node_modules/rc-select/es/util.js","original":{"line":124,"column":2}},{"generated":{"line":153,"column":7},"source":"../node_modules/rc-select/es/util.js","original":{"line":124,"column":7}},{"name":"i","generated":{"line":153,"column":11},"source":"../node_modules/rc-select/es/util.js","original":{"line":124,"column":11}},{"generated":{"line":153,"column":15},"source":"../node_modules/rc-select/es/util.js","original":{"line":124,"column":15}},{"generated":{"line":153,"column":16},"source":"../node_modules/rc-select/es/util.js","original":{"line":124,"column":2}},{"name":"i","generated":{"line":153,"column":18},"source":"../node_modules/rc-select/es/util.js","original":{"line":124,"column":18}},{"name":"separators","generated":{"line":153,"column":22},"source":"../node_modules/rc-select/es/util.js","original":{"line":124,"column":22}},{"name":"length","generated":{"line":153,"column":33},"source":"../node_modules/rc-select/es/util.js","original":{"line":124,"column":33}},{"generated":{"line":153,"column":39},"source":"../node_modules/rc-select/es/util.js","original":{"line":124,"column":2}},{"generated":{"line":153,"column":41},"source":"../node_modules/rc-select/es/util.js","original":{"line":124,"column":41}},{"name":"i","generated":{"line":153,"column":43},"source":"../node_modules/rc-select/es/util.js","original":{"line":124,"column":43}},{"generated":{"line":153,"column":44},"source":"../node_modules/rc-select/es/util.js","original":{"line":124,"column":2}},{"generated":{"line":153,"column":46},"source":"../node_modules/rc-select/es/util.js","original":{"line":124,"column":46}},{"generated":{"line":154,"column":0},"source":"../node_modules/rc-select/es/util.js","original":{"line":125,"column":4}},{"name":"string","generated":{"line":154,"column":8},"source":"../node_modules/rc-select/es/util.js","original":{"line":125,"column":8}},{"name":"lastIndexOf","generated":{"line":154,"column":15},"source":"../node_modules/rc-select/es/util.js","original":{"line":125,"column":15}},{"generated":{"line":154,"column":26},"source":"../node_modules/rc-select/es/util.js","original":{"line":125,"column":8}},{"name":"separators","generated":{"line":154,"column":27},"source":"../node_modules/rc-select/es/util.js","original":{"line":125,"column":27}},{"name":"i","generated":{"line":154,"column":38},"source":"../node_modules/rc-select/es/util.js","original":{"line":125,"column":38}},{"generated":{"line":154,"column":39},"source":"../node_modules/rc-select/es/util.js","original":{"line":125,"column":27}},{"generated":{"line":154,"column":40},"source":"../node_modules/rc-select/es/util.js","original":{"line":125,"column":8}},{"generated":{"line":154,"column":44},"source":"../node_modules/rc-select/es/util.js","original":{"line":125,"column":44}},{"generated":{"line":154,"column":45},"source":"../node_modules/rc-select/es/util.js","original":{"line":125,"column":4}},{"generated":{"line":154,"column":47},"source":"../node_modules/rc-select/es/util.js","original":{"line":125,"column":47}},{"generated":{"line":155,"column":0},"source":"../node_modules/rc-select/es/util.js","original":{"line":126,"column":6}},{"generated":{"line":155,"column":13},"source":"../node_modules/rc-select/es/util.js","original":{"line":126,"column":13}},{"generated":{"line":155,"column":17},"source":"../node_modules/rc-select/es/util.js","original":{"line":126,"column":6}},{"generated":{"line":156,"column":0},"source":"../node_modules/rc-select/es/util.js","original":{"line":127,"column":5}},{"generated":{"line":157,"column":0},"source":"../node_modules/rc-select/es/util.js","original":{"line":128,"column":3}},{"generated":{"line":158,"column":0},"source":"../node_modules/rc-select/es/util.js","original":{"line":129,"column":2}},{"generated":{"line":158,"column":9},"source":"../node_modules/rc-select/es/util.js","original":{"line":129,"column":9}},{"generated":{"line":158,"column":14},"source":"../node_modules/rc-select/es/util.js","original":{"line":129,"column":2}},{"generated":{"line":159,"column":0},"source":"../node_modules/rc-select/es/util.js","original":{"line":130,"column":1}},{"generated":{"line":161,"column":0},"source":"../node_modules/rc-select/es/util.js","original":{"line":132,"column":7}},{"name":"splitBySeparators","generated":{"line":161,"column":9},"source":"../node_modules/rc-select/es/util.js","original":{"line":132,"column":16}},{"generated":{"line":161,"column":26},"source":"../node_modules/rc-select/es/util.js","original":{"line":132,"column":7}},{"name":"string","generated":{"line":161,"column":27},"source":"../node_modules/rc-select/es/util.js","original":{"line":132,"column":34}},{"generated":{"line":161,"column":33},"source":"../node_modules/rc-select/es/util.js","original":{"line":132,"column":7}},{"name":"separators","generated":{"line":161,"column":35},"source":"../node_modules/rc-select/es/util.js","original":{"line":132,"column":42}},{"generated":{"line":161,"column":45},"source":"../node_modules/rc-select/es/util.js","original":{"line":132,"column":7}},{"generated":{"line":161,"column":47},"source":"../node_modules/rc-select/es/util.js","original":{"line":132,"column":54}},{"generated":{"line":162,"column":0},"source":"../node_modules/rc-select/es/util.js","original":{"line":133,"column":2}},{"name":"reg","generated":{"line":162,"column":6},"source":"../node_modules/rc-select/es/util.js","original":{"line":133,"column":6}},{"generated":{"line":162,"column":12},"source":"../node_modules/rc-select/es/util.js","original":{"line":133,"column":12}},{"name":"RegExp","generated":{"line":162,"column":16},"source":"../node_modules/rc-select/es/util.js","original":{"line":133,"column":16}},{"generated":{"line":162,"column":22},"source":"../node_modules/rc-select/es/util.js","original":{"line":133,"column":12}},{"generated":{"line":162,"column":23},"source":"../node_modules/rc-select/es/util.js","original":{"line":133,"column":23}},{"name":"separators","generated":{"line":162,"column":29},"source":"../node_modules/rc-select/es/util.js","original":{"line":133,"column":29}},{"name":"join","generated":{"line":162,"column":40},"source":"../node_modules/rc-select/es/util.js","original":{"line":133,"column":40}},{"generated":{"line":162,"column":44},"source":"../node_modules/rc-select/es/util.js","original":{"line":133,"column":29}},{"generated":{"line":162,"column":46},"source":"../node_modules/rc-select/es/util.js","original":{"line":133,"column":23}},{"generated":{"line":162,"column":49},"source":"../node_modules/rc-select/es/util.js","original":{"line":133,"column":49}},{"generated":{"line":162,"column":52},"source":"../node_modules/rc-select/es/util.js","original":{"line":133,"column":12}},{"generated":{"line":162,"column":53},"source":"../node_modules/rc-select/es/util.js","original":{"line":133,"column":2}},{"generated":{"line":163,"column":0},"source":"../node_modules/rc-select/es/util.js","original":{"line":134,"column":2}},{"name":"string","generated":{"line":163,"column":9},"source":"../node_modules/rc-select/es/util.js","original":{"line":134,"column":9}},{"name":"split","generated":{"line":163,"column":16},"source":"../node_modules/rc-select/es/util.js","original":{"line":134,"column":16}},{"generated":{"line":163,"column":21},"source":"../node_modules/rc-select/es/util.js","original":{"line":134,"column":9}},{"name":"reg","generated":{"line":163,"column":22},"source":"../node_modules/rc-select/es/util.js","original":{"line":134,"column":22}},{"generated":{"line":163,"column":25},"source":"../node_modules/rc-select/es/util.js","original":{"line":134,"column":9}},{"name":"filter","generated":{"line":163,"column":27},"source":"../node_modules/rc-select/es/util.js","original":{"line":134,"column":27}},{"generated":{"line":163,"column":33},"source":"../node_modules/rc-select/es/util.js","original":{"line":134,"column":9}},{"generated":{"line":163,"column":34},"source":"../node_modules/rc-select/es/util.js","original":{"line":134,"column":34}},{"name":"token","generated":{"line":163,"column":44},"source":"../node_modules/rc-select/es/util.js","original":{"line":134,"column":44}},{"generated":{"line":163,"column":49},"source":"../node_modules/rc-select/es/util.js","original":{"line":134,"column":34}},{"generated":{"line":163,"column":51},"source":"../node_modules/rc-select/es/util.js","original":{"line":134,"column":51}},{"generated":{"line":164,"column":0},"source":"../node_modules/rc-select/es/util.js","original":{"line":135,"column":4}},{"name":"token","generated":{"line":164,"column":11},"source":"../node_modules/rc-select/es/util.js","original":{"line":135,"column":11}},{"generated":{"line":164,"column":16},"source":"../node_modules/rc-select/es/util.js","original":{"line":135,"column":4}},{"generated":{"line":165,"column":0},"source":"../node_modules/rc-select/es/util.js","original":{"line":136,"column":3}},{"generated":{"line":165,"column":3},"source":"../node_modules/rc-select/es/util.js","original":{"line":134,"column":9}},{"generated":{"line":165,"column":4},"source":"../node_modules/rc-select/es/util.js","original":{"line":134,"column":2}},{"generated":{"line":166,"column":0},"source":"../node_modules/rc-select/es/util.js","original":{"line":137,"column":1}},{"generated":{"line":168,"column":0},"source":"../node_modules/rc-select/es/util.js","original":{"line":139,"column":7}},{"name":"defaultFilterFn","generated":{"line":168,"column":9},"source":"../node_modules/rc-select/es/util.js","original":{"line":139,"column":16}},{"generated":{"line":168,"column":24},"source":"../node_modules/rc-select/es/util.js","original":{"line":139,"column":7}},{"name":"input","generated":{"line":168,"column":25},"source":"../node_modules/rc-select/es/util.js","original":{"line":139,"column":32}},{"generated":{"line":168,"column":30},"source":"../node_modules/rc-select/es/util.js","original":{"line":139,"column":7}},{"name":"child","generated":{"line":168,"column":32},"source":"../node_modules/rc-select/es/util.js","original":{"line":139,"column":39}},{"generated":{"line":168,"column":37},"source":"../node_modules/rc-select/es/util.js","original":{"line":139,"column":7}},{"generated":{"line":168,"column":39},"source":"../node_modules/rc-select/es/util.js","original":{"line":139,"column":46}},{"generated":{"line":169,"column":0},"source":"../node_modules/rc-select/es/util.js","original":{"line":140,"column":2}},{"name":"String","generated":{"line":169,"column":9},"source":"../node_modules/rc-select/es/util.js","original":{"line":140,"column":9}},{"name":"getPropValue","generated":{"line":169,"column":16},"source":"../node_modules/rc-select/es/util.js","original":{"line":140,"column":16}},{"name":"child","generated":{"line":169,"column":29},"source":"../node_modules/rc-select/es/util.js","original":{"line":140,"column":29}},{"generated":{"line":169,"column":34},"source":"../node_modules/rc-select/es/util.js","original":{"line":140,"column":16}},{"generated":{"line":169,"column":36},"source":"../node_modules/rc-select/es/util.js","original":{"line":140,"column":36}},{"name":"props","generated":{"line":169,"column":41},"source":"../node_modules/rc-select/es/util.js","original":{"line":140,"column":41}},{"generated":{"line":169,"column":46},"source":"../node_modules/rc-select/es/util.js","original":{"line":140,"column":36}},{"name":"optionFilterProp","generated":{"line":169,"column":47},"source":"../node_modules/rc-select/es/util.js","original":{"line":140,"column":47}},{"generated":{"line":169,"column":63},"source":"../node_modules/rc-select/es/util.js","original":{"line":140,"column":16}},{"generated":{"line":169,"column":64},"source":"../node_modules/rc-select/es/util.js","original":{"line":140,"column":9}},{"name":"indexOf","generated":{"line":169,"column":66},"source":"../node_modules/rc-select/es/util.js","original":{"line":140,"column":66}},{"generated":{"line":169,"column":73},"source":"../node_modules/rc-select/es/util.js","original":{"line":140,"column":9}},{"name":"input","generated":{"line":169,"column":74},"source":"../node_modules/rc-select/es/util.js","original":{"line":140,"column":74}},{"generated":{"line":169,"column":79},"source":"../node_modules/rc-select/es/util.js","original":{"line":140,"column":9}},{"generated":{"line":169,"column":83},"source":"../node_modules/rc-select/es/util.js","original":{"line":140,"column":83}},{"generated":{"line":169,"column":84},"source":"../node_modules/rc-select/es/util.js","original":{"line":140,"column":84}},{"generated":{"line":169,"column":85},"source":"../node_modules/rc-select/es/util.js","original":{"line":140,"column":2}},{"generated":{"line":170,"column":0},"source":"../node_modules/rc-select/es/util.js","original":{"line":141,"column":1}},{"generated":{"line":172,"column":0},"source":"../node_modules/rc-select/es/util.js","original":{"line":143,"column":7}},{"name":"validateOptionValue","generated":{"line":172,"column":9},"source":"../node_modules/rc-select/es/util.js","original":{"line":143,"column":16}},{"generated":{"line":172,"column":28},"source":"../node_modules/rc-select/es/util.js","original":{"line":143,"column":7}},{"name":"value","generated":{"line":172,"column":29},"source":"../node_modules/rc-select/es/util.js","original":{"line":143,"column":36}},{"generated":{"line":172,"column":34},"source":"../node_modules/rc-select/es/util.js","original":{"line":143,"column":7}},{"name":"props","generated":{"line":172,"column":36},"source":"../node_modules/rc-select/es/util.js","original":{"line":143,"column":43}},{"generated":{"line":172,"column":41},"source":"../node_modules/rc-select/es/util.js","original":{"line":143,"column":7}},{"generated":{"line":172,"column":43},"source":"../node_modules/rc-select/es/util.js","original":{"line":143,"column":50}},{"generated":{"line":173,"column":0},"source":"../node_modules/rc-select/es/util.js","original":{"line":144,"column":2}},{"name":"isSingleMode","generated":{"line":173,"column":6},"source":"../node_modules/rc-select/es/util.js","original":{"line":144,"column":6}},{"name":"props","generated":{"line":173,"column":19},"source":"../node_modules/rc-select/es/util.js","original":{"line":144,"column":19}},{"generated":{"line":173,"column":24},"source":"../node_modules/rc-select/es/util.js","original":{"line":144,"column":6}},{"name":"isMultiple","generated":{"line":173,"column":29},"source":"../node_modules/rc-select/es/util.js","original":{"line":144,"column":29}},{"name":"props","generated":{"line":173,"column":40},"source":"../node_modules/rc-select/es/util.js","original":{"line":144,"column":40}},{"generated":{"line":173,"column":45},"source":"../node_modules/rc-select/es/util.js","original":{"line":144,"column":29}},{"generated":{"line":173,"column":46},"source":"../node_modules/rc-select/es/util.js","original":{"line":144,"column":2}},{"generated":{"line":173,"column":48},"source":"../node_modules/rc-select/es/util.js","original":{"line":144,"column":48}},{"generated":{"line":174,"column":0},"source":"../node_modules/rc-select/es/util.js","original":{"line":145,"column":4}},{"generated":{"line":175,"column":0},"source":"../node_modules/rc-select/es/util.js","original":{"line":146,"column":3}},{"generated":{"line":176,"column":0},"source":"../node_modules/rc-select/es/util.js","original":{"line":147,"column":2}},{"generated":{"line":176,"column":6},"source":"../node_modules/rc-select/es/util.js","original":{"line":147,"column":6}},{"name":"value","generated":{"line":176,"column":13},"source":"../node_modules/rc-select/es/util.js","original":{"line":147,"column":13}},{"generated":{"line":176,"column":18},"source":"../node_modules/rc-select/es/util.js","original":{"line":147,"column":6}},{"generated":{"line":176,"column":23},"source":"../node_modules/rc-select/es/util.js","original":{"line":147,"column":23}},{"generated":{"line":176,"column":31},"source":"../node_modules/rc-select/es/util.js","original":{"line":147,"column":2}},{"generated":{"line":176,"column":33},"source":"../node_modules/rc-select/es/util.js","original":{"line":147,"column":33}},{"generated":{"line":177,"column":0},"source":"../node_modules/rc-select/es/util.js","original":{"line":148,"column":4}},{"generated":{"line":177,"column":10},"source":"../node_modules/rc-select/es/util.js","original":{"line":148,"column":10}},{"name":"Error","generated":{"line":177,"column":14},"source":"../node_modules/rc-select/es/util.js","original":{"line":148,"column":14}},{"generated":{"line":177,"column":19},"source":"../node_modules/rc-select/es/util.js","original":{"line":148,"column":10}},{"generated":{"line":177,"column":20},"source":"../node_modules/rc-select/es/util.js","original":{"line":148,"column":20}},{"generated":{"line":177,"column":50},"source":"../node_modules/rc-select/es/util.js","original":{"line":148,"column":50}},{"name":"value","generated":{"line":177,"column":57},"source":"../node_modules/rc-select/es/util.js","original":{"line":148,"column":57}},{"generated":{"line":177,"column":62},"source":"../node_modules/rc-select/es/util.js","original":{"line":148,"column":20}},{"generated":{"line":177,"column":65},"source":"../node_modules/rc-select/es/util.js","original":{"line":148,"column":65}},{"generated":{"line":177,"column":89},"source":"../node_modules/rc-select/es/util.js","original":{"line":148,"column":20}},{"generated":{"line":177,"column":92},"source":"../node_modules/rc-select/es/util.js","original":{"line":148,"column":92}},{"generated":{"line":177,"column":143},"source":"../node_modules/rc-select/es/util.js","original":{"line":148,"column":10}},{"generated":{"line":177,"column":144},"source":"../node_modules/rc-select/es/util.js","original":{"line":148,"column":4}},{"generated":{"line":178,"column":0},"source":"../node_modules/rc-select/es/util.js","original":{"line":149,"column":3}},{"generated":{"line":179,"column":0},"source":"../node_modules/rc-select/es/util.js","original":{"line":150,"column":1}},{"generated":{"line":181,"column":0},"source":"../node_modules/rc-select/es/util.js","original":{"line":152,"column":7}},{"name":"saveRef","generated":{"line":181,"column":9},"source":"../node_modules/rc-select/es/util.js","original":{"line":152,"column":16}},{"generated":{"line":181,"column":16},"source":"../node_modules/rc-select/es/util.js","original":{"line":152,"column":7}},{"name":"instance","generated":{"line":181,"column":17},"source":"../node_modules/rc-select/es/util.js","original":{"line":152,"column":24}},{"generated":{"line":181,"column":25},"source":"../node_modules/rc-select/es/util.js","original":{"line":152,"column":7}},{"name":"name","generated":{"line":181,"column":27},"source":"../node_modules/rc-select/es/util.js","original":{"line":152,"column":34}},{"generated":{"line":181,"column":31},"source":"../node_modules/rc-select/es/util.js","original":{"line":152,"column":7}},{"generated":{"line":181,"column":33},"source":"../node_modules/rc-select/es/util.js","original":{"line":152,"column":40}},{"generated":{"line":182,"column":0},"source":"../node_modules/rc-select/es/util.js","original":{"line":153,"column":2}},{"generated":{"line":182,"column":9},"source":"../node_modules/rc-select/es/util.js","original":{"line":153,"column":9}},{"name":"node","generated":{"line":182,"column":19},"source":"../node_modules/rc-select/es/util.js","original":{"line":153,"column":19}},{"generated":{"line":182,"column":23},"source":"../node_modules/rc-select/es/util.js","original":{"line":153,"column":9}},{"generated":{"line":182,"column":25},"source":"../node_modules/rc-select/es/util.js","original":{"line":153,"column":25}},{"name":"instance","generated":{"line":183,"column":0},"source":"../node_modules/rc-select/es/util.js","original":{"line":154,"column":4}},{"name":"name","generated":{"line":183,"column":13},"source":"../node_modules/rc-select/es/util.js","original":{"line":154,"column":13}},{"generated":{"line":183,"column":17},"source":"../node_modules/rc-select/es/util.js","original":{"line":154,"column":4}},{"name":"node","generated":{"line":183,"column":21},"source":"../node_modules/rc-select/es/util.js","original":{"line":154,"column":21}},{"generated":{"line":183,"column":25},"source":"../node_modules/rc-select/es/util.js","original":{"line":154,"column":4}},{"generated":{"line":184,"column":0},"source":"../node_modules/rc-select/es/util.js","original":{"line":155,"column":3}},{"generated":{"line":184,"column":3},"source":"../node_modules/rc-select/es/util.js","original":{"line":153,"column":2}},{"generated":{"line":185,"column":0},"source":"../node_modules/rc-select/es/util.js","original":{"line":156,"column":1}}],"sources":{"../node_modules/rc-select/es/util.js":"import React from 'react';\n\nexport function getValuePropValue(child) {\n  var props = child.props;\n  if ('value' in props) {\n    return props.value;\n  }\n  if (child.key) {\n    return child.key;\n  }\n  if (child.type && child.type.isSelectOptGroup && props.label) {\n    return props.label;\n  }\n  throw new Error('Need at least a key or a value or a label (only for OptGroup) for ' + child);\n}\n\nexport function getPropValue(child, prop) {\n  if (prop === 'value') {\n    return getValuePropValue(child);\n  }\n  return child.props[prop];\n}\n\nexport function isMultiple(props) {\n  return props.multiple;\n}\n\nexport function isCombobox(props) {\n  return props.combobox;\n}\n\nexport function isMultipleOrTags(props) {\n  return props.multiple || props.tags;\n}\n\nexport function isMultipleOrTagsOrCombobox(props) {\n  return isMultipleOrTags(props) || isCombobox(props);\n}\n\nexport function isSingleMode(props) {\n  return !isMultipleOrTagsOrCombobox(props);\n}\n\nexport function toArray(value) {\n  var ret = value;\n  if (value === undefined) {\n    ret = [];\n  } else if (!Array.isArray(value)) {\n    ret = [value];\n  }\n  return ret;\n}\n\nexport function preventDefaultEvent(e) {\n  e.preventDefault();\n}\n\nexport function findIndexInValueByKey(value, key) {\n  var index = -1;\n  for (var i = 0; i < value.length; i++) {\n    if (value[i].key === key) {\n      index = i;\n      break;\n    }\n  }\n  return index;\n}\n\nexport function findIndexInValueByLabel(value, label) {\n  var index = -1;\n  for (var i = 0; i < value.length; i++) {\n    if (toArray(value[i].label).join('') === label) {\n      index = i;\n      break;\n    }\n  }\n  return index;\n}\n\nexport function getSelectKeys(menuItems, value) {\n  if (value === null || value === undefined) {\n    return [];\n  }\n  var selectedKeys = [];\n  React.Children.forEach(menuItems, function (item) {\n    if (item.type.isMenuItemGroup) {\n      selectedKeys = selectedKeys.concat(getSelectKeys(item.props.children, value));\n    } else {\n      var itemValue = getValuePropValue(item);\n      var itemKey = item.key;\n      if (findIndexInValueByKey(value, itemValue) !== -1 && itemKey) {\n        selectedKeys.push(itemKey);\n      }\n    }\n  });\n  return selectedKeys;\n}\n\nexport var UNSELECTABLE_STYLE = {\n  userSelect: 'none',\n  WebkitUserSelect: 'none'\n};\n\nexport var UNSELECTABLE_ATTRIBUTE = {\n  unselectable: 'unselectable'\n};\n\nexport function findFirstMenuItem(children) {\n  for (var i = 0; i < children.length; i++) {\n    var child = children[i];\n    if (child.type.isMenuItemGroup) {\n      var found = findFirstMenuItem(child.props.children);\n      if (found) {\n        return found;\n      }\n    } else if (!child.props.disabled) {\n      return child;\n    }\n  }\n  return null;\n}\n\nexport function includesSeparators(string, separators) {\n  for (var i = 0; i < separators.length; ++i) {\n    if (string.lastIndexOf(separators[i]) > 0) {\n      return true;\n    }\n  }\n  return false;\n}\n\nexport function splitBySeparators(string, separators) {\n  var reg = new RegExp('[' + separators.join() + ']');\n  return string.split(reg).filter(function (token) {\n    return token;\n  });\n}\n\nexport function defaultFilterFn(input, child) {\n  return String(getPropValue(child, this.props.optionFilterProp)).indexOf(input) > -1;\n}\n\nexport function validateOptionValue(value, props) {\n  if (isSingleMode(props) || isMultiple(props)) {\n    return;\n  }\n  if (typeof value !== 'string') {\n    throw new Error('Invalid `value` of type `' + typeof value + '` supplied to Option, ' + 'expected `string` when `tags/combobox` is `true`.');\n  }\n}\n\nexport function saveRef(instance, name) {\n  return function (node) {\n    instance[name] = node;\n  };\n}"},"lineCount":null}},"hash":"ffc3e83756a637cda915891a982da197","cacheData":{"env":{}}}